bpfmaps/__init__.py
bpfmaps/libbpf/__init__.py
bpfmaps/libbpf/libbpf.so.0.8.0
bpfmaps-0.0.8.dist-info/LICENSE
bpfmaps-0.0.8.dist-info/METADATA
bpfmaps-0.0.8.dist-info/WHEEL
bpfmaps-0.0.8.dist-info/top_level.txt
bpfmaps-0.0.8.dist-info/RECORD
