Metadata-Version: 2.1
Name: bpfmaps
Version: 0.0.8
Summary: Python wrapper of libbpf to interact with bpf maps
Home-page: https://github.com/PeterStolz/pybpfmaps
Author: Peter Stolz
Author-email: 50801264+PeterStolz@users.noreply.github.com
Project-URL: Bug Tracker, https://github.com/PeterStolz/pybpfmaps/issues
Keywords: eBPF,bpfmaps,libbpf
Platform: linux
Classifier: Development Status :: 3 - Alpha
Classifier: Intended Audience :: Developers
Classifier: Programming Language :: Python :: 3.10
Classifier: License :: OSI Approved :: Apache Software License
Classifier: Natural Language :: English
Classifier: Operating System :: POSIX :: Linux
Requires-Python: >=3.10
License-File: LICENSE
